msn_weather_wrapper/__init__.py
msn_weather_wrapper/client.py
msn_weather_wrapper/models.py
msn_weather_wrapper/py.typed
msn_weather_wrapper-1.9.11.dist-info/METADATA
msn_weather_wrapper-1.9.11.dist-info/WHEEL
msn_weather_wrapper-1.9.11.dist-info/licenses/LICENSE
msn_weather_wrapper-1.9.11.dist-info/RECORD
