Metadata-Version: 2.4
Name: msn-weather-wrapper
Version: 1.9.11
Summary: A production-ready Python wrapper for MSN Weather with automatic versioning and CI/CD
Project-URL: Homepage, https://github.com/jim-wyatt/msn-weather-wrapper
Project-URL: Repository, https://github.com/jim-wyatt/msn-weather-wrapper
Project-URL: Issues, https://github.com/jim-wyatt/msn-weather-wrapper/issues
Author-email: Jim Wyatt <the.jim.wyatt@outlook.com>
License: MIT
License-File: LICENSE
Classifier: Development Status :: 3 - Alpha
Classifier: Intended Audience :: Developers
Classifier: License :: OSI Approved :: MIT License
Classifier: Programming Language :: Python :: 3
Classifier: Programming Language :: Python :: 3.10
Classifier: Programming Language :: Python :: 3.11
Classifier: Programming Language :: Python :: 3.12
Requires-Python: >=3.10
Requires-Dist: beautifulsoup4>=4.14.0
Requires-Dist: flasgger>=0.9.7
Requires-Dist: flask-cors>=6.0.0
Requires-Dist: flask-limiter>=3.5.0
Requires-Dist: flask>=3.1.0
Requires-Dist: geopy>=2.4.0
Requires-Dist: gunicorn>=23.0.0
Requires-Dist: lxml>=6.0.0
Requires-Dist: pydantic>=2.12.0
Requires-Dist: python-dotenv>=1.0.0
Requires-Dist: requests>=2.32.0
Requires-Dist: structlog>=24.1.0
Provides-Extra: dev
Requires-Dist: bandit>=1.7.0; extra == 'dev'
Requires-Dist: mkdocs-material>=9.5.0; extra == 'dev'
Requires-Dist: mkdocs>=1.5.0; extra == 'dev'
Requires-Dist: mypy>=1.8.0; extra == 'dev'
Requires-Dist: pip-audit>=2.7.0; extra == 'dev'
Requires-Dist: pip-licenses>=4.3.0; extra == 'dev'
Requires-Dist: pre-commit>=3.5.0; extra == 'dev'
Requires-Dist: pymdown-extensions>=10.7.0; extra == 'dev'
Requires-Dist: pytest-asyncio>=0.23.0; extra == 'dev'
Requires-Dist: pytest-benchmark>=4.0.0; extra == 'dev'
Requires-Dist: pytest-cov>=5.0.0; extra == 'dev'
Requires-Dist: pytest-xdist>=3.6.0; extra == 'dev'
Requires-Dist: pytest>=8.0.0; extra == 'dev'
Requires-Dist: python-semantic-release>=9.0.0; extra == 'dev'
Requires-Dist: ruff>=0.14.0; extra == 'dev'
Requires-Dist: safety>=3.0.0; extra == 'dev'
Requires-Dist: types-beautifulsoup4>=4.12.0; extra == 'dev'
Requires-Dist: types-requests>=2.32.0; extra == 'dev'
